{
  "Id": "0147e912-ff8d-46d9-965a-dee0789ef32b",
  "Name": "Windows Disk Cleanup Manager",
  "Description": "Installs Windows Disk Cleanup manager on Windows 2008, 2008-R2 and 2012 Server.  Should work on Windows 7 and 8",
  "ActionType": "Octopus.Script",
  "Version": 4,
  "Properties": {
    "Octopus.Action.Script.Syntax": "PowerShell",
    "Octopus.Action.Script.ScriptBody": "__SOURCE_FILE__:scriptbody.ps1"
  },
  "SensitiveProperties": {},
  "Parameters": [
    {
      "Name": "driveLetter",
      "Label": "Drive Letter",
      "HelpText": "The driver letter in which to run the clean up manager on, by default C.",
      "DefaultValue": "C",
      "DisplaySettings": {
        "Octopus.ControlType": "Select",
        "Octopus.SelectOptions": "C\nD\nE\nF\nG\nH\nI\nJ\nK\nL\nM\nN\nO\nP\nQ\nR\nS\nT\nU\nV\nW\nX\nY\nZ"
      }
    },
    {
      "Name": "cleanupSwitch",
      "Label": "Clean up Level",
      "HelpText": "2 options are LOWDISK or VERYLOWDISK, varies the level of cleanup that is done.  VERYLOWDISK is the most complete, most cleaned up.",
      "DefaultValue": "VERYLOWDISK",
      "DisplaySettings": {
        "Octopus.ControlType": "Select",
        "Octopus.SelectOptions": "VERYLOWDISK| Very Low Disk\nLOWDISK\\Low Disk"
      }
    }
  ],
  "LastModifiedOn": "2015-10-12T11:46:26.0670000-07:00",
  "LastModifiedBy": "dbloch",
  "$Meta": {
    "ExportedAt": "2015-10-12T12:07:41.6760000-07:00",
    "OctopusVersion": "3.0.21.0",
    "Type": "ActionTemplate"
  },
  "Category": "windows"
}
