{
  "Id": "140d22e8-abe9-4a32-aab7-20af667c6255",
  "Name": "Azure Website - Load App Settings From File (Geta)",
  "Description": "Loads app settings from a json file (e.g. local.settings.json) which is also json-transformed to inject environment-specific values.",
  "ActionType": "Octopus.AzurePowerShell",
  "Version": 7,
  "CommunityActionTemplateId": null,
  "Packages": [
    {
      "Id": "31f79f978a2e46f9b3add02f695e672b",
      "Name": "LoadAppSettingsFromFile.Package",
      "PackageId": "#{Parameters.PackageId}",
      "FeedId": null,
      "AcquisitionLocation": "Server",
      "Properties": {
        "Extract": "True"
      }
    }
  ],
  "Properties": {
    "Octopus.Action.Script.ScriptSource": "Inline",
    "Octopus.Action.Azure.AccountId": "#{Azure.Subscription.Name}",
    "Octopus.Action.Package.JsonConfigurationVariablesEnabled": "True",
    "Octopus.Action.EnabledFeatures": "Octopus.Features.JsonConfigurationVariables",
    "Octopus.Action.Package.JsonConfigurationVariablesTargets": "#{Parameters.SettingsFile.Path}",
    "Octopus.Action.Script.ScriptFileName": null,
    "Octopus.Action.Package.PackageId": "#{Utilities.PackageId}",
    "Octopus.Action.Package.FeedId": "feeds-builtin",
    "Octopus.Action.Package.DownloadOnTentacle": "False",
    "Octopus.Action.Script.Syntax": "PowerShell",
    "Octopus.Action.Script.ScriptBody": "__SOURCE_FILE__:scriptbody.ps1"
  },
  "Parameters": [
    {
      "Id": "e21c4265-7e92-4893-a359-3d8c4b0223c2",
      "Name": "Parameters.ResourceGroup.Name",
      "Label": "Resource group name",
      "HelpText": "Name of the target resource group.",
      "DefaultValue": "",
      "DisplaySettings": {
        "Octopus.ControlType": "SingleLineText"
      }
    },
    {
      "Id": "4485ab2e-2003-4fab-814f-90ce9a338cce",
      "Name": "Parameters.WebApp.Name",
      "Label": "Webapp / function name",
      "HelpText": "Name of the target webapp.",
      "DefaultValue": "",
      "DisplaySettings": {
        "Octopus.ControlType": "SingleLineText"
      }
    },
    {
      "Id": "f589143a-3f46-4a2b-b14f-02469ed80c19",
      "Name": "Parameters.SettingsFile.Path",
      "Label": "Settings file path",
      "HelpText": "Path of the JSON settings file relative to script directory. Or in most of the cases easiest is to use Octopus Action variable for the extract path: `#{Octopus.Action.Package[LoadAppSettingsFromFile.Package].ExtractedPath}`",
      "DefaultValue": "",
      "DisplaySettings": {
        "Octopus.ControlType": "SingleLineText"
      }
    },
    {
      "Id": "fb46e50c-283a-4d7d-b4ec-2a171f76d8c4",
      "Name": "Parameters.DeploySlot.Name",
      "Label": "Deploy slot name",
      "HelpText": "Name of the deploy slot. Production slot will be updated if left blank.",
      "DefaultValue": "",
      "DisplaySettings": {
        "Octopus.ControlType": "SingleLineText"
      }
    },
    {
      "Id": "81b491a9-e1f5-4b22-b9d2-22df2bb60686",
      "Name": "Parameters.PackageId",
      "Label": "Package Id",
      "HelpText": "Id of the referenced package which when extracted might contain the settings file.",
      "DefaultValue": "",
      "DisplaySettings": {
        "Octopus.ControlType": "SingleLineText"
      }
    }
  ],
  "LastModifiedBy": "sarbis",
  "$Meta": {
    "ExportedAt": "2019-01-22T09:58:08.8110000Z",
    "OctopusVersion": "2018.10.0",
    "Type": "ActionTemplate"
  },
  "Category": "azure"
}
